.coveragerc
.gitignore
CHANGES.txt
MANIFEST.in
README.txt
buildout.cfg
development.ini
package.json
production.ini
pytest.ini
setup.py
webpack.config.js
profiles/versions.cfg
xxx/__init__.py
xxx.server_api.egg-info/PKG-INFO
xxx.server_api.egg-info/SOURCES.txt
xxx.server_api.egg-info/dependency_links.txt
xxx.server_api.egg-info/entry_points.txt
xxx.server_api.egg-info/namespace_packages.txt
xxx.server_api.egg-info/not-zip-safe
xxx.server_api.egg-info/requires.txt
xxx.server_api.egg-info/top_level.txt
xxx/server_api/__init__.py
xxx/server_api/constants.py
xxx/server_api/design.py
xxx/server_api/models.py
xxx/server_api/utils.py
xxx/server_api/views.py
xxx/server_api/static/bundle.js
xxx/server_api/static/favicon.ico
xxx/server_api/static/robots.txt
xxx/server_api/static/theme.css
xxx/server_api/static/angular_source/app.js
xxx/server_api/static/angular_source/controllers/authCtrl.js
xxx/server_api/static/angular_source/controllers/detailCtrl.js
xxx/server_api/static/angular_source/controllers/indexCtrl.js
xxx/server_api/static/angular_source/controllers/mypageCtrl.js
xxx/server_api/static/angular_source/controllers/tablesCtrl.js
xxx/server_api/static/angular_source/filters/filters.js
xxx/server_api/static/angular_source/services/couchdbService.js
xxx/server_api/static/angular_source/services/webappService.js
xxx/server_api/static/angular_source/templates/add_post.html
xxx/server_api/static/angular_source/templates/base.html
xxx/server_api/static/angular_source/templates/detail.html
xxx/server_api/static/angular_source/templates/forgot-password.html
xxx/server_api/static/angular_source/templates/index.html
xxx/server_api/static/angular_source/templates/login.html
xxx/server_api/static/angular_source/templates/mypage.html
xxx/server_api/static/angular_source/templates/register.html
xxx/server_api/static/angular_source/templates/tables.html
xxx/server_api/static/css/sb-admin.css
xxx/server_api/static/js/sb-admin-charts.js
xxx/server_api/static/js/sb-admin-charts.min.js
xxx/server_api/static/js/sb-admin-datatables.js
xxx/server_api/static/js/sb-admin-datatables.min.js
xxx/server_api/static/js/sb-admin.js
xxx/server_api/static/pug/blank.pug
xxx/server_api/static/pug/cards.pug
xxx/server_api/static/pug/charts.pug
xxx/server_api/static/pug/forgot-password.pug
