Metadata-Version: 2.1
Name: xxx.server-api
Version: 0.37.5
Summary: xxx
Home-page: UNKNOWN
Author: 
Author-email: 
License: UNKNOWN
Keywords: web pyramid pylons
Platform: UNKNOWN
Classifier: Programming Language :: Python
Classifier: Framework :: Pyramid
Provides-Extra: testing
